vizdato/__init__.py
vizdato/_nbdev.py
vizdato/core.py
vizdato-0.0.2.dist-info/LICENSE
vizdato-0.0.2.dist-info/METADATA
vizdato-0.0.2.dist-info/WHEEL
vizdato-0.0.2.dist-info/entry_points.txt
vizdato-0.0.2.dist-info/top_level.txt
vizdato-0.0.2.dist-info/RECORD
