Metadata-Version: 2.1
Name: vizdato
Version: 0.0.2
Summary: Automatically visualize and explore data
Home-page: https://github.com/ryanfras/vizdato/tree/master/
Author: Ryan Fraser
Author-email: ryanfras@gmail.com
License: Apache Software License 2.0
Keywords: visualize explore data auto
Platform: UNKNOWN
Classifier: Development Status :: 3 - Alpha
Classifier: Intended Audience :: Developers
Classifier: License :: OSI Approved :: Apache Software License
Classifier: Natural Language :: English
Classifier: Programming Language :: Python :: 3.6
Classifier: Programming Language :: Python :: 3.7
Classifier: Programming Language :: Python :: 3.8
Requires-Python: >=3.6
